cli/__init__.py
cli/cli.py
cli/config.py
cli/yolo_segment_to_labelme.py
cli/utils/__init__.py
cli/utils/check_file_exist.py
cli/utils/handle_label_mapping.py
cli/utils/statistics_helper.py
utils/__init__.py
utils/check_file_exist.py
utils/handle_label_mapping.py
utils/statistics_helper.py
label_tool-0.0.1a2.dist-info/LICENSE
label_tool-0.0.1a2.dist-info/METADATA
label_tool-0.0.1a2.dist-info/WHEEL
label_tool-0.0.1a2.dist-info/entry_points.txt
label_tool-0.0.1a2.dist-info/top_level.txt
label_tool-0.0.1a2.dist-info/RECORD
